magic_i18n/__init__.py
magic_i18n/asgi.py
magic_i18n/lint.py
magic_i18n/text.py
magic_i18n/utils.py
magic_i18n-0.3.dist-info/licenses/LICENSE.md
magic_i18n-0.3.dist-info/METADATA
magic_i18n-0.3.dist-info/WHEEL
magic_i18n-0.3.dist-info/entry_points.txt
magic_i18n-0.3.dist-info/top_level.txt
magic_i18n-0.3.dist-info/RECORD
