Metadata-Version: 2.4
Name: magic-i18n
Version: 0.3
Summary: Text internationalization with async context magic
Author-email: Dmitrii Vlasov <scailer@yandex.ru>
License: MIT License
Project-URL: Homepage, https://github.com/scailer/magic-i18n
Project-URL: Repository, https://github.com/scailer/magic-i18n.git
Project-URL: Changelog, https://github.com/scailer/magic-i18n/blob/master/CHANGELOG
Keywords: i18n,internationalization,async,contextvar,asgi
Classifier: Development Status :: 4 - Beta
Classifier: Environment :: Plugins
Classifier: Intended Audience :: Developers
Classifier: License :: OSI Approved :: MIT License
Classifier: Programming Language :: Python
Classifier: Programming Language :: Python :: 3
Classifier: Programming Language :: Python :: 3.11
Classifier: Programming Language :: Python :: 3.12
Classifier: Programming Language :: Python :: 3.13
Classifier: Programming Language :: Python :: 3.14
Classifier: Topic :: Software Development :: Libraries :: Python Modules
Classifier: Framework :: AsyncIO
Requires-Python: >=3.11
License-File: LICENSE.md
Provides-Extra: spell
Requires-Dist: pyspellchecker; extra == "spell"
Provides-Extra: dev
Requires-Dist: pytest; extra == "dev"
Requires-Dist: pytest-asyncio; extra == "dev"
Requires-Dist: pytest-cov; extra == "dev"
Requires-Dist: pytest-runner; extra == "dev"
Requires-Dist: coverage; extra == "dev"
Requires-Dist: ruff; extra == "dev"
Requires-Dist: mypy; extra == "dev"
Requires-Dist: pyspellchecker; extra == "dev"
Dynamic: license-file
